LICENSE.txt
README.md
setup.cfg
setup.py
animeHours/animeHours.py
animeHours.egg-info/PKG-INFO
animeHours.egg-info/SOURCES.txt
animeHours.egg-info/dependency_links.txt
animeHours.egg-info/requires.txt
animeHours.egg-info/top_level.txt