Metadata-Version: 2.1
Name: animeHours
Version: 0.2
Summary: Find the amount of hours you took to watch the anime you love.
Home-page: https://github.com/Greeny127/AnimeHoursFinder
Author: Greeny127
License: MIT
Download-URL: https://github.com/Greeny127/AnimeHoursFinder/archive/refs/tags/v_01.tar.gz
Keywords: ANIME,HOURS,MYANIMELIST,MAL,TOTAL
Platform: UNKNOWN
Classifier: Development Status :: 3 - Alpha
Classifier: Intended Audience :: Developers
Classifier: Topic :: Software Development :: Build Tools
Classifier: License :: OSI Approved :: MIT License
Classifier: Programming Language :: Python :: 3.7
